entity_history/__init__.py
entity_history/apps.py
entity_history/models.py
entity_history/urls.py
entity_history/version.py
entity_history/migrations/0001_initial.py
entity_history/migrations/0002_auto_20150406_1605.py
entity_history/migrations/0003_update_triggers.py
entity_history/migrations/0004_update_triggers_and_foreign_keys.py
entity_history/migrations/0005_auto_20180108_2021.py
entity_history/migrations/__init__.py
entity_history/sql/__init__.py
entity_history/sql/entity_activation_procedure_create.sql
entity_history/sql/entity_activation_procedure_delete.sql
entity_history/sql/entity_activation_trigger_create.sql
entity_history/sql/entity_activation_trigger_delete.sql
entity_history/sql/entity_relationship_activation_procedure_create.sql
entity_history/sql/entity_relationship_activation_procedure_delete.sql
entity_history/sql/entity_relationship_activation_trigger_create.sql
entity_history/sql/entity_relationship_activation_trigger_delete.sql
entity_history/sql/entity_relationship_activation_trigger_immediate_create.sql
entity_history/sql/foreign_keys.py
entity_history/sql/foreign_keys_cascade_delete.sql
entity_history/sql/triggers.py
entity_history/tests/__init__.py
entity_history/tests/cascade_tests.py
entity_history/tests/entity_activation_tests.py
entity_history/tests/entity_history_tests.py
entity_history/tests/entity_relationship_activation_tests.py
entity_history/tests/trigger_tests.py
django_entity_history-2.0.0.dist-info/LICENSE
django_entity_history-2.0.0.dist-info/METADATA
django_entity_history-2.0.0.dist-info/WHEEL
django_entity_history-2.0.0.dist-info/top_level.txt
django_entity_history-2.0.0.dist-info/RECORD
