Metadata-Version: 2.1
Name: django-entity-history
Version: 2.0.0
Summary: History about Django Entities
Home-page: https://github.com/ambitioninc/django-entity-history
Author: Wes Kendall
Author-email: opensource@ambition.com
License: MIT
Classifier: Programming Language :: Python
Classifier: Programming Language :: Python :: 3.7
Classifier: Programming Language :: Python :: 3.8
Classifier: Programming Language :: Python :: 3.9
Classifier: Intended Audience :: Developers
Classifier: License :: OSI Approved :: MIT License
Classifier: Operating System :: OS Independent
Classifier: Framework :: Django
Classifier: Framework :: Django :: 3.2
Classifier: Framework :: Django :: 4.0
Classifier: Framework :: Django :: 4.1
Classifier: Framework :: Django :: 4.2
License-File: LICENSE
Requires-Dist: Django (>3.2)
Requires-Dist: django-entity (>=6.1.0)
Requires-Dist: psycopg2
